zdock_parser/__init__.py
zdock_parser-0.13.dist-info/LICENSE
zdock_parser-0.13.dist-info/METADATA
zdock_parser-0.13.dist-info/WHEEL
zdock_parser-0.13.dist-info/top_level.txt
zdock_parser-0.13.dist-info/RECORD
