Metadata-Version: 2.1
Name: zdock-parser
Version: 0.13
Summary: ZDOCK output file parser
Home-page: https://github.com/capslockwizard/zdock-parser
Author: Justin Chan
Author-email: capslockwizard@gmail.com
License: UNKNOWN
Platform: UNKNOWN
Classifier: Environment :: Plugins
Classifier: Intended Audience :: Science/Research
Classifier: Topic :: Scientific/Engineering :: Bio-Informatics
Classifier: Programming Language :: Python :: 2.7
Classifier: License :: OSI Approved :: MIT License
Classifier: Operating System :: POSIX :: Linux
Classifier: Operating System :: MacOS
Classifier: Development Status :: 5 - Production/Stable
Requires-Dist: numba
Requires-Dist: numpy
Requires-Dist: MDAnalysis
Requires-Dist: drsip-common
